makebib/__init__.py
makebib/about.py
makebib/makebib.py
makebib-0.2.2.dist-info/DESCRIPTION.rst
makebib-0.2.2.dist-info/METADATA
makebib-0.2.2.dist-info/RECORD
makebib-0.2.2.dist-info/WHEEL
makebib-0.2.2.dist-info/entry_points.txt
makebib-0.2.2.dist-info/metadata.json
makebib-0.2.2.dist-info/top_level.txt
