Metadata-Version: 2.0
Name: makebib
Version: 0.2.2
Summary: A simple script to generate a local bib file from a central database.
Home-page: https://gitlab.com/Verner/makebib
Author: Jonathan L. Verner
Author-email: jonathan@temno.eu
License: MIT
Keywords: bibtex latex
Platform: UNKNOWN
Classifier: Development Status :: 3 - Alpha
Classifier: Intended Audience :: Science/Research
Classifier: Topic :: Scientific/Engineering :: Mathematics
Classifier: Topic :: Text Processing :: Markup :: LaTeX
Classifier: License :: OSI Approved :: MIT License
Classifier: Programming Language :: Python :: 2
Classifier: Programming Language :: Python :: 2.7
Classifier: Programming Language :: Python :: 3
Classifier: Programming Language :: Python :: 3.3
Classifier: Programming Language :: Python :: 3.4
Classifier: Programming Language :: Python :: 3.5
Requires-Dist: pybtex
